quantaroute_geocoding/__init__.py
quantaroute_geocoding/cli.py
quantaroute_geocoding/client.py
quantaroute_geocoding/csv_processor.py
quantaroute_geocoding/exceptions.py
quantaroute_geocoding/location_lookup.py
quantaroute_geocoding/offline.py
quantaroute_geocoding-1.0.7.dist-info/licenses/LICENSE
quantaroute_geocoding-1.0.7.dist-info/METADATA
quantaroute_geocoding-1.0.7.dist-info/WHEEL
quantaroute_geocoding-1.0.7.dist-info/entry_points.txt
quantaroute_geocoding-1.0.7.dist-info/top_level.txt
quantaroute_geocoding-1.0.7.dist-info/RECORD
