Metadata-Version: 2.4
Name: quantaroute-geocoding
Version: 1.0.7
Summary: Revolutionary Python SDK for QuantaRoute Geocoding API with Location Lookup and offline DigiPin processing
Home-page: https://github.com/quantaroute/quantaroute-geocoding-python
Author: QuantaRoute
Author-email: QuantaRoute <hello@quantaroute.com>
License: MIT
Project-URL: Homepage, https://quantaroute.com
Project-URL: Documentation, https://api.quantaroute.com/v1/digipin/docs
Project-URL: Repository, https://github.com/quantaroute/quantaroute-geocoding-python
Project-URL: Bug Tracker, https://github.com/quantaroute/quantaroute-geocoding-python/issues
Keywords: geocoding,digipin,gis,location,india,address,coordinates,administrative-boundaries,pincode,postal-lookup,location-intelligence
Classifier: Development Status :: 4 - Beta
Classifier: Intended Audience :: Developers
Classifier: License :: OSI Approved :: MIT License
Classifier: Operating System :: OS Independent
Classifier: Programming Language :: Python :: 3
Classifier: Programming Language :: Python :: 3.7
Classifier: Programming Language :: Python :: 3.8
Classifier: Programming Language :: Python :: 3.9
Classifier: Programming Language :: Python :: 3.10
Classifier: Programming Language :: Python :: 3.11
Classifier: Topic :: Scientific/Engineering :: GIS
Classifier: Topic :: Software Development :: Libraries :: Python Modules
Requires-Python: >=3.7
License-File: LICENSE
Requires-Dist: requests>=2.25.0
Requires-Dist: pandas>=1.3.0
Requires-Dist: digipin>=1.0.0
Requires-Dist: tqdm>=4.60.0
Requires-Dist: click>=8.0.0
Provides-Extra: dev
Requires-Dist: pytest>=6.0; extra == "dev"
Requires-Dist: pytest-cov>=2.0; extra == "dev"
Requires-Dist: black>=21.0; extra == "dev"
Requires-Dist: flake8>=3.8; extra == "dev"
Requires-Dist: mypy>=0.910; extra == "dev"
Dynamic: author
Dynamic: home-page
Dynamic: license-file
Dynamic: requires-python
